model_runner_client/__init__.py
model_runner_client/errors/__init__.py
model_runner_client/errors/errors.py
model_runner_client/grpc/generated/__init__.py
model_runner_client/grpc/generated/__init__.pyi
model_runner_client/grpc/generated/commons_pb2.py
model_runner_client/grpc/generated/commons_pb2.pyi
model_runner_client/grpc/generated/commons_pb2_grpc.py
model_runner_client/grpc/generated/dynamic_subclass_pb2.py
model_runner_client/grpc/generated/dynamic_subclass_pb2.pyi
model_runner_client/grpc/generated/dynamic_subclass_pb2_grpc.py
model_runner_client/grpc/generated/train_infer_pb2.py
model_runner_client/grpc/generated/train_infer_pb2.pyi
model_runner_client/grpc/generated/train_infer_pb2_grpc.py
model_runner_client/grpc/protos/commons.proto
model_runner_client/grpc/protos/dynamic_subclass.proto
model_runner_client/grpc/protos/train_infer.proto
model_runner_client/model_cluster.py
model_runner_client/model_concurrent_runners/__init__.py
model_runner_client/model_concurrent_runners/dynamic_subclass_model_concurrent_runner.py
model_runner_client/model_concurrent_runners/model_concurrent_runner.py
model_runner_client/model_runners/__init__.py
model_runner_client/model_runners/dynamic_subclass_model_runner.py
model_runner_client/model_runners/model_runner.py
model_runner_client/security/__init__.py
model_runner_client/security/credentials.py
model_runner_client/security/grpc_auth_interceptor.py
model_runner_client/security/tls_peer_key.py
model_runner_client/security/wallet_gelegation.py
model_runner_client/utils/__init__.py
model_runner_client/utils/datatype_transformer.py
model_runner_client/websocket_client.py
model_runner_client-0.10.0.dist-info/METADATA
model_runner_client-0.10.0.dist-info/WHEEL
model_runner_client-0.10.0.dist-info/RECORD
