Metadata-Version: 2.4
Name: model-runner-client
Version: 0.10.0
Summary: Model Runner Client is a Python library that allows Coordinators to manage real-time model synchronization and perform concurrent predictions on distributed model nodes within a Crunch.
Author: boutrig abdennour
Author-email: abdennour.boutrig@crunchdao.com
Requires-Python: >=3.11,<4.0
Classifier: Programming Language :: Python :: 3
Classifier: Programming Language :: Python :: 3.11
Classifier: Programming Language :: Python :: 3.12
Classifier: Programming Language :: Python :: 3.13
Classifier: Programming Language :: Python :: 3.14
Requires-Dist: base58 (>=2.1.1,<3.0.0)
Requires-Dist: cryptography (>=46.0.3,<47.0.0)
Requires-Dist: grpcio (>=1,<2)
Requires-Dist: grpcio-health-checking (>=1.74.0,<2.0.0)
Requires-Dist: pandas (>=2.2.3,<3.0.0)
Requires-Dist: websockets (>=14.2,<15.0)
